{
  "main": {
    "id": "37a4ece0ae44376a",
    "type": "split",
    "children": [
      {
        "id": "aefcb22fe2ec86a0",
        "type": "tabs",
        "children": [
          {
            "id": "b2a8bf73aaf7f8e2",
            "type": "leaf",
            "state": {
              "type": "empty",
              "state": {}
            }
          }
        ]
      }
    ],
    "direction": "vertical"
  },
  "left": {
    "id": "033576a6b33dff69",
    "type": "split",
    "children": [
      {
        "id": "d32bd3e9f2db57a0",
        "type": "tabs",
        "dimension": 30.900473933649288,
        "children": [
          {
            "id": "df59f08946ce9655",
            "type": "leaf",
            "state": {
              "type": "calendar",
              "state": {}
            }
          },
          {
            "id": "e2f9ecf537a853a4",
            "type": "leaf",
            "state": {
              "type": "bookmarks",
              "state": {}
            }
          }
        ]
      },
      {
        "id": "90362f6f602f507d",
        "type": "tabs",
        "dimension": 69.0995260663507,
        "children": [
          {
            "id": "318abbbcd7749f6f",
            "type": "leaf",
            "state": {
              "type": "file-explorer",
              "state": {
                "sortOrder": "alphabetical"
              }
            }
          },
          {
            "id": "cc8540b919f4ee67",
            "type": "leaf",
            "state": {
              "type": "search",
              "state": {
                "query": "",
                "matchingCase": false,
                "explainSearch": false,
                "collapseAll": false,
                "extraContext": false,
                "sortOrder": "alphabetical"
              }
            }
          },
          {
            "id": "9b78bc0e4508fc3f",
            "type": "leaf",
            "state": {
              "type": "tag",
              "state": {
                "sortOrder": "frequency",
                "useHierarchy": true
              }
            }
          }
        ]
      }
    ],
    "direction": "horizontal",
    "width": 313.5
  },
  "right": {
    "id": "e909704c2c67d329",
    "type": "split",
    "children": [
      {
        "id": "8d590967b738185b",
        "type": "tabs",
        "children": [
          {
            "id": "bfe60a9c435028cc",
            "type": "leaf",
            "state": {
              "type": "outgoing-link",
              "state": {
                "linksCollapsed": false,
                "unlinkedCollapsed": true
              }
            }
          },
          {
            "id": "6d086e2d3fce45ca",
            "type": "leaf",
            "state": {
              "type": "outline",
              "state": {}
            }
          },
          {
            "id": "fdf26b19b598132b",
            "type": "leaf",
            "state": {
              "type": "backlink",
              "state": {
                "collapseAll": false,
                "extraContext": false,
                "sortOrder": "alphabetical",
                "showSearch": false,
                "searchQuery": "",
                "backlinkCollapsed": false,
                "unlinkedCollapsed": true
              }
            }
          }
        ]
      }
    ],
    "direction": "horizontal",
    "width": 356.5,
    "collapsed": true
  },
  "left-ribbon": {
    "hiddenItems": {
      "canvas:新建白板": false,
      "switcher:打开快速切换": false,
      "graph:查看关系图谱": false,
      "command-palette:打开命令面板": false,
      "workspaces:管理工作区布局": false,
      "random-note:开始漫游笔记": false,
      "templater-obsidian:Templater": false,
      "periodic-notes:Open today": false
    }
  },
  "active": "b2a8bf73aaf7f8e2",
  "lastOpenFiles": [
    "PeriodicNotes/2023/Monthly/2023-06.md",
    "PeriodicNotes/2023/Weekly/2023-W23.md",
    "PeriodicNotes/2023/Weekly/2023-W22.md",
    "PeriodicNotes/2023/Daily/06/2023-06-01.md",
    "PeriodicNotes/2023/Daily/06/2023-06-02.md",
    "PeriodicNotes/2023/Daily/06/2023-06-03.md",
    "1. Projects/分享-2023 WOT 分享会/演讲排练/逐字稿.md",
    "PeriodicNotes/2023/2023-Q1.md",
    "PeriodicNotes/2023/2023.md",
    "1. Projects/分享-2023 WOT 分享会/README.md",
    "TASK.md"
  ]
}